django_manifold-1.4.dist-info/DESCRIPTION.rst
django_manifold-1.4.dist-info/LICENSE.txt
django_manifold-1.4.dist-info/METADATA
django_manifold-1.4.dist-info/RECORD
django_manifold-1.4.dist-info/WHEEL
django_manifold-1.4.dist-info/metadata.json
django_manifold-1.4.dist-info/top_level.txt
manifold/__init__.py
manifold/apps.py
manifold/file.py
manifold/handler.py
manifold/http.py
manifold/rpc.py
manifold/serialize.py
manifold/testing.py
manifold/validators.py
manifold/management/__init__.py
manifold/management/commands/__init__.py
manifold/management/commands/runrpcserver.py
