Metadata-Version: 2.0
Name: django-manifold
Version: 1.4
Summary: A python library that implements a thrift parser into Django to use it's models and controllers to implement RPC/HTTP services. 
Home-page: https://www.acvauctions.com
Author: ACV Auctions
Author-email: dstarner@acvauctions.com
License: Apache 2.0 License
Platform: UNKNOWN
Classifier: Environment :: Web Environment
Classifier: Framework :: Django
Classifier: Framework :: Django :: 2.0
Classifier: Intended Audience :: Developers
Classifier: License :: OSI Approved :: Apache Software License
Classifier: Operating System :: OS Independent
Classifier: Programming Language :: Python
Classifier: Programming Language :: Python :: 3.5
Classifier: Programming Language :: Python :: 3.6
Requires-Dist: Django
Requires-Dist: gunicorn-thrift
Requires-Dist: thriftpy
